MANIFEST.in
setup.py
tests/__init__.py
tests/test_enviroment.py
tests/test_todoist.py
todoist_to_markdown/__init__.py
todoist_to_markdown/argument.py
todoist_to_markdown/enviroment.py
todoist_to_markdown/main.py
todoist_to_markdown/task.py
todoist_to_markdown/todoist.py
todoist_to_markdown.egg-info/PKG-INFO
todoist_to_markdown.egg-info/SOURCES.txt
todoist_to_markdown.egg-info/dependency_links.txt
todoist_to_markdown.egg-info/entry_points.txt
todoist_to_markdown.egg-info/requires.txt
todoist_to_markdown.egg-info/top_level.txt