Metadata-Version: 1.0
Name: todoist-to-markdown
Version: 1.0
Summary: Pythonプロジェクトのテンプレート。主にCLIを作るときに利用する予定
Home-page: https://github.com/koboriakira/todoist-to-markdown
Author: Kobori Akira
Author-email: private.beats@gmail.com
License: UNKNOWN
Platform: UNKNOWN
